<?xml version="1.0" encoding="utf-8"?>
<EntityRelationships>
  <EntityRelationship Name="new_contact_new_procurement_contactperson">
    <EntityRelationshipType>OneToMany</EntityRelationshipType>
    <IsCustomizable>1</IsCustomizable>
    <IntroducedVersion>1.0</IntroducedVersion>
    <IsHierarchical>0</IsHierarchical>
    <ReferencingEntityName>new_procurement</ReferencingEntityName>
    <ReferencedEntityName>Contact</ReferencedEntityName>
    <CascadeAssign>NoCascade</CascadeAssign>
    <CascadeDelete>RemoveLink</CascadeDelete>
    <CascadeReparent>NoCascade</CascadeReparent>
    <CascadeShare>NoCascade</CascadeShare>
    <CascadeUnshare>NoCascade</CascadeUnshare>
    <CascadeRollupView>NoCascade</CascadeRollupView>
    <IsValidForAdvancedFind>1</IsValidForAdvancedFind>
    <ReferencingAttributeName>new_contactperson</ReferencingAttributeName>
    <RelationshipDescription>
      <Descriptions>
        <Description description="" languagecode="1033" />
      </Descriptions>
    </RelationshipDescription>
    <EntityRelationshipRoles>
      <EntityRelationshipRole>
        <NavPaneDisplayOption>UseCollectionName</NavPaneDisplayOption>
        <NavPaneArea>Details</NavPaneArea>
        <NavPaneOrder>10000</NavPaneOrder>
        <NavigationPropertyName>new_contactperson</NavigationPropertyName>
        <CustomLabels>
          <CustomLabel description="" languagecode="1033" />
        </CustomLabels>
        <RelationshipRoleType>1</RelationshipRoleType>
      </EntityRelationshipRole>
      <EntityRelationshipRole>
        <NavigationPropertyName>new_contact_new_procurement_contactperson</NavigationPropertyName>
        <RelationshipRoleType>0</RelationshipRoleType>
      </EntityRelationshipRole>
    </EntityRelationshipRoles>
  </EntityRelationship>
  <EntityRelationship Name="new_contact_quote_ContactPerson">
    <EntityRelationshipType>OneToMany</EntityRelationshipType>
    <IsCustomizable>1</IsCustomizable>
    <IntroducedVersion>1.0</IntroducedVersion>
    <IsHierarchical>0</IsHierarchical>
    <ReferencingEntityName>Quote</ReferencingEntityName>
    <ReferencedEntityName>Contact</ReferencedEntityName>
    <CascadeAssign>NoCascade</CascadeAssign>
    <CascadeDelete>RemoveLink</CascadeDelete>
    <CascadeReparent>NoCascade</CascadeReparent>
    <CascadeShare>NoCascade</CascadeShare>
    <CascadeUnshare>NoCascade</CascadeUnshare>
    <CascadeRollupView>NoCascade</CascadeRollupView>
    <IsValidForAdvancedFind>1</IsValidForAdvancedFind>
    <ReferencingAttributeName>new_ContactPerson</ReferencingAttributeName>
    <RelationshipDescription>
      <Descriptions>
        <Description description="" languagecode="1033" />
      </Descriptions>
    </RelationshipDescription>
    <EntityRelationshipRoles>
      <EntityRelationshipRole>
        <NavPaneDisplayOption>UseCollectionName</NavPaneDisplayOption>
        <NavPaneArea>Details</NavPaneArea>
        <NavPaneOrder>10000</NavPaneOrder>
        <NavigationPropertyName>new_ContactPerson</NavigationPropertyName>
        <CustomLabels>
          <CustomLabel description="" languagecode="1033" />
        </CustomLabels>
        <RelationshipRoleType>1</RelationshipRoleType>
      </EntityRelationshipRole>
      <EntityRelationshipRole>
        <NavigationPropertyName>new_contact_quote_ContactPerson</NavigationPropertyName>
        <RelationshipRoleType>0</RelationshipRoleType>
      </EntityRelationshipRole>
    </EntityRelationshipRoles>
  </EntityRelationship>
</EntityRelationships>